{
    "neighborhoods": [
        {
            "name": "Le Marais",
            "alternate_names": [
                "The Marsh",
                "Jewish Quarter"
            ],
            "character": "A historic and vibrant area known for its narrow cobblestone streets and diverse cultural offerings.",
            "location": {
                "central": true,
                "description": "Located in the 3rd and 4th arrondissements on the Right Bank of the Seine.",
                "borders": [
                    "Bastille",
                    "Île de la Cité",
                    "République"
                ],
                "landmarks": [
                    "Place des Vosges",
                    "Musée Picasso"
                ]
            },
            "history": {
                "overview": "Originally a marshland, it became a royal district in the 17th century and later a Jewish quarter.",
                "significance": "Home to historic mansions and a vibrant Jewish community.",
                "notable_events": [
                    "The district's transformation in the 19th century",
                    "Significant Jewish migration"
                ]
            },
            "practical_info": {
                "transit": [
                    "Saint-Paul",
                    "Hôtel de Ville",
                    "Chemin Vert"
                ],
                "safety": "Generally safe with bustling streets, especially in tourist areas.",
                "best_time_to_visit": "Spring and early fall for pleasant weather.",
                "walkability": "Highly walkable with many pedestrian areas."
            },
            "appeal": {
                "known_for": [
                    "Art galleries",
                    "Boutique shopping",
                    "Historic architecture"
                ],
                "atmosphere": [
                    "Charming",
                    "Cultural",
                    "Trendy"
                ],
                "best_for": [
                    "Art lovers",
                    "History buffs",
                    "Fashion enthusiasts"
                ]
            },
            "categories": {
                "touristy": 4,
                "residential": 3,
                "green_spaces": 2,
                "shopping": 5,
                "dining": 5,
                "nightlife": 4,
                "cultural": 5,
                "historic": 5
            },
            "highlights": {
                "attractions": [
                    {
                        "name": "Place des Vosges",
                        "type": "Historic square",
                        "description": "The oldest planned square in Paris, surrounded by elegant 17th-century architecture.",
                        "appeal": "A beautiful and peaceful retreat in the heart of the city."
                    },
                    {
                        "name": "Musée Picasso",
                        "type": "Museum",
                        "description": "Houses over 5,000 works by Pablo Picasso.",
                        "appeal": "A must-visit for modern art enthusiasts."
                    },
                    {
                        "name": "Le Carreau du Temple",
                        "type": "Event venue",
                        "description": "A cultural venue hosting markets, exhibitions, and performances.",
                        "appeal": "Experience local arts and crafts in a historical setting."
                    }
                ],
                "dining": [
                    {
                        "name": "L'As du Fallafel",
                        "cuisine": "Middle Eastern",
                        "price_range": "€",
                        "known_for": "Famous falafel sandwiches",
                        "atmosphere": "Casual and lively"
                    },
                    {
                        "name": "Le Mary Celeste",
                        "cuisine": "Contemporary",
                        "price_range": "€€",
                        "known_for": "Oysters and creative cocktails",
                        "atmosphere": "Trendy with a nautical theme"
                    },
                    {
                        "name": "Chez Janou",
                        "cuisine": "Provençal",
                        "price_range": "€€",
                        "known_for": "Chocolate mousse and sunny terrace",
                        "atmosphere": "Cozy and Provencal"
                    }
                ],
                "activities": [
                    {
                        "name": "Art Gallery Tour",
                        "type": "Cultural activity",
                        "description": "Explore the numerous art galleries showcasing contemporary works.",
                        "suitable_for": [
                            "Art enthusiasts",
                            "Couples"
                        ]
                    },
                    {
                        "name": "Shopping at BHV Marais",
                        "type": "Shopping",
                        "description": "A large department store offering a variety of goods.",
                        "suitable_for": [
                            "Shoppers",
                            "Families"
                        ]
                    }
                ]
            },
            "stay_here_if": [
                "You love art and history",
                "You want to be in a trendy area with many dining options"
            ],
            "avoid_if": [
                "You prefer quieter, less crowded areas",
                "You need more green spaces"
            ],
            "insider_tips": [
                "Visit on a Sunday when most other stores in Paris are closed.",
                "Explore Rue des Rosiers for the best Jewish bakeries."
            ]
        },
        {
            "name": "Saint-Germain-des-Prés",
            "alternate_names": [
                "Saint-Germain",
                "The Left Bank"
            ],
            "character": "An intellectual and artistic hub with a rich history of literary and cultural achievements.",
            "location": {
                "central": true,
                "description": "Situated in the 6th arrondissement on the Left Bank of the Seine.",
                "borders": [
                    "Latin Quarter",
                    "Montparnasse",
                    "The Seine"
                ],
                "landmarks": [
                    "Saint-Germain-des-Prés Church",
                    "Café de Flore"
                ]
            },
            "history": {
                "overview": "A center for existentialist thought and home to famous writers and philosophers.",
                "significance": "Known for its cafes where intellectuals gathered, like Sartre and Hemingway.",
                "notable_events": [
                    "Post-WWII existentialist movement",
                    "Literary gatherings"
                ]
            },
            "practical_info": {
                "transit": [
                    "Saint-Germain-des-Prés",
                    "Mabillon",
                    "Sèvres-Babylone"
                ],
                "safety": "Safe and well-patrolled, popular with tourists and locals alike.",
                "best_time_to_visit": "Year-round; the vibrant cafe culture is always inviting.",
                "walkability": "Very walkable with many pedestrian-friendly streets."
            },
            "appeal": {
                "known_for": [
                    "Café culture",
                    "Art galleries",
                    "Boutique shopping"
                ],
                "atmosphere": [
                    "Sophisticated",
                    "Historic",
                    "Intellectual"
                ],
                "best_for": [
                    "Literature lovers",
                    "Café enthusiasts",
                    "Art aficionados"
                ]
            },
            "categories": {
                "touristy": 4,
                "residential": 3,
                "green_spaces": 3,
                "shopping": 4,
                "dining": 5,
                "nightlife": 3,
                "cultural": 5,
                "historic": 5
            },
            "highlights": {
                "attractions": [
                    {
                        "name": "Saint-Germain-des-Prés Church",
                        "type": "Historic church",
                        "description": "One of the oldest churches in Paris with stunning architecture.",
                        "appeal": "A testament to Paris's medieval past."
                    },
                    {
                        "name": "Café de Flore",
                        "type": "Café",
                        "description": "One of the oldest and most prestigious coffeehouses in Paris.",
                        "appeal": "Famous for its literary and philosophical patrons."
                    },
                    {
                        "name": "Musée d'Orsay",
                        "type": "Museum",
                        "description": "Houses the largest collection of impressionist and post-impressionist masterpieces.",
                        "appeal": "A must-see for art lovers."
                    }
                ],
                "dining": [
                    {
                        "name": "Les Deux Magots",
                        "cuisine": "Traditional French",
                        "price_range": "€€€",
                        "known_for": "Historic literary haunt",
                        "atmosphere": "Classic and upscale"
                    },
                    {
                        "name": "Ladurée",
                        "cuisine": "French Patisserie",
                        "price_range": "€€",
                        "known_for": "Famous macarons and pastries",
                        "atmosphere": "Elegant and sweet"
                    },
                    {
                        "name": "Le Procope",
                        "cuisine": "French",
                        "price_range": "€€€",
                        "known_for": "Oldest café in Paris",
                        "atmosphere": "Historic and charming"
                    }
                ],
                "activities": [
                    {
                        "name": "Bookstore Browsing",
                        "type": "Cultural activity",
                        "description": "Explore independent bookstores with rich literary selections.",
                        "suitable_for": [
                            "Book lovers",
                            "Intellectuals"
                        ]
                    },
                    {
                        "name": "Gallery Hopping",
                        "type": "Art appreciation",
                        "description": "Visit numerous art galleries featuring contemporary and classic works.",
                        "suitable_for": [
                            "Art enthusiasts",
                            "Couples"
                        ]
                    }
                ]
            },
            "stay_here_if": [
                "You appreciate a rich cultural history",
                "You enjoy café culture"
            ],
            "avoid_if": [
                "You're on a tight budget",
                "You prefer modern architecture"
            ],
            "insider_tips": [
                "Visit early in the morning to enjoy the area before it gets busy.",
                "Try the hot chocolate at the famous Café de Flore."
            ]
        },
        {
            "name": "Montmartre",
            "alternate_names": [
                "The Butte",
                "Artists' Quarter"
            ],
            "character": "A bohemian neighborhood known for its artistic history and breathtaking views of Paris.",
            "location": {
                "central": false,
                "description": "Located in the 18th arrondissement on a large hill in the north of Paris.",
                "borders": [
                    "Pigalle",
                    "Clignancourt",
                    "La Chapelle"
                ],
                "landmarks": [
                    "Sacré-Cœur Basilica",
                    "Place du Tertre"
                ]
            },
            "history": {
                "overview": "Once a rural village, it became a hub for artists like Picasso and Van Gogh in the late 19th century.",
                "significance": "Known for its cabarets and studios of famous artists.",
                "notable_events": [
                    "The rise of bohemian culture in late 19th century",
                    "Home of the Moulin Rouge"
                ]
            },
            "practical_info": {
                "transit": [
                    "Abbesses",
                    "Anvers",
                    "Lamarck-Caulaincourt"
                ],
                "safety": "Generally safe, but be cautious of pickpockets in crowded areas.",
                "best_time_to_visit": "Early morning or late afternoon for fewer crowds.",
                "walkability": "Challenging due to steep hills but rewarding with picturesque streets."
            },
            "appeal": {
                "known_for": [
                    "Artistic heritage",
                    "Panoramic views",
                    "Historic cabarets"
                ],
                "atmosphere": [
                    "Bohemian",
                    "Picturesque",
                    "Charming"
                ],
                "best_for": [
                    "Artists",
                    "Romantics",
                    "Photographers"
                ]
            },
            "categories": {
                "touristy": 5,
                "residential": 3,
                "green_spaces": 4,
                "shopping": 3,
                "dining": 4,
                "nightlife": 3,
                "cultural": 5,
                "historic": 5
            },
            "highlights": {
                "attractions": [
                    {
                        "name": "Sacré-Cœur Basilica",
                        "type": "Religious monument",
                        "description": "A stunning white basilica offering panoramic views of Paris.",
                        "appeal": "Iconic architecture and sweeping city views."
                    },
                    {
                        "name": "Place du Tertre",
                        "type": "Public square",
                        "description": "A lively square filled with artists and cafes.",
                        "appeal": "Experience Parisian art and culture in action."
                    },
                    {
                        "name": "Moulin Rouge",
                        "type": "Cabaret",
                        "description": "The world-famous cabaret known for its can-can dance.",
                        "appeal": "An iconic symbol of Parisian nightlife."
                    }
                ],
                "dining": [
                    {
                        "name": "Le Consulat",
                        "cuisine": "French",
                        "price_range": "€€",
                        "known_for": "Historic artist hangout",
                        "atmosphere": "Quaint and historic"
                    },
                    {
                        "name": "La Maison Rose",
                        "cuisine": "French",
                        "price_range": "€€",
                        "known_for": "Picturesque setting",
                        "atmosphere": "Charming and cozy"
                    },
                    {
                        "name": "Le Relais Gascon",
                        "cuisine": "Southwestern French",
                        "price_range": "€€",
                        "known_for": "Generous portions and salads",
                        "atmosphere": "Rustic and friendly"
                    }
                ],
                "activities": [
                    {
                        "name": "Walking Tour",
                        "type": "Guided tour",
                        "description": "Explore the history and art of Montmartre with a local guide.",
                        "suitable_for": [
                            "History buffs",
                            "Families"
                        ]
                    },
                    {
                        "name": "Wine Tasting",
                        "type": "Culinary experience",
                        "description": "Discover local wines in a traditional Parisian setting.",
                        "suitable_for": [
                            "Wine enthusiasts",
                            "Couples"
                        ]
                    }
                ]
            },
            "stay_here_if": [
                "You love art and history",
                "You want a romantic setting with great views"
            ],
            "avoid_if": [
                "You dislike hilly terrain",
                "You prefer quieter, less touristy areas"
            ],
            "insider_tips": [
                "Visit the hidden vineyard, Clos Montmartre.",
                "Avoid Place du Tertre at peak hours for a more authentic experience."
            ]
        },
        {
            "name": "Latin Quarter",
            "alternate_names": [
                "Quartier Latin",
                "Student District"
            ],
            "character": "A lively and historic district known for its educational institutions and vibrant street life.",
            "location": {
                "central": true,
                "description": "Situated in the 5th and part of the 6th arrondissements on the Left Bank.",
                "borders": [
                    "Saint-Germain-des-Prés",
                    "Jardin des Plantes",
                    "Île de la Cité"
                ],
                "landmarks": [
                    "Sorbonne University",
                    "Panthéon"
                ]
            },
            "history": {
                "overview": "The heart of academic life in Paris since the Middle Ages, named for the Latin spoken by students.",
                "significance": "Home to the University of Paris and a hub for intellectual activity.",
                "notable_events": [
                    "May 1968 student protests",
                    "Medieval scholasticism"
                ]
            },
            "practical_info": {
                "transit": [
                    "Cluny - La Sorbonne",
                    "Saint-Michel",
                    "Cardinal Lemoine"
                ],
                "safety": "Generally safe, with a bustling student population.",
                "best_time_to_visit": "Spring for the lively student atmosphere and blooming gardens.",
                "walkability": "Very walkable with narrow, winding streets."
            },
            "appeal": {
                "known_for": [
                    "Academic heritage",
                    "Lively cafés",
                    "Bookshops"
                ],
                "atmosphere": [
                    "Intellectual",
                    "Historic",
                    "Boisterous"
                ],
                "best_for": [
                    "Students",
                    "History enthusiasts",
                    "Culture seekers"
                ]
            },
            "categories": {
                "touristy": 4,
                "residential": 3,
                "green_spaces": 3,
                "shopping": 3,
                "dining": 4,
                "nightlife": 3,
                "cultural": 5,
                "historic": 5
            },
            "highlights": {
                "attractions": [
                    {
                        "name": "Panthéon",
                        "type": "Historical monument",
                        "description": "A mausoleum containing the remains of distinguished French citizens.",
                        "appeal": "Architectural grandeur and a who's who of French history."
                    },
                    {
                        "name": "Jardin du Luxembourg",
                        "type": "Public park",
                        "description": "A beautifully manicured garden with statues and fountains.",
                        "appeal": "Perfect for a leisurely stroll or a picnic."
                    },
                    {
                        "name": "Shakespeare and Company",
                        "type": "Bookstore",
                        "description": "A famous English-language bookstore and literary haven.",
                        "appeal": "A must-visit for book lovers and literary history enthusiasts."
                    }
                ],
                "dining": [
                    {
                        "name": "Le Procope",
                        "cuisine": "French",
                        "price_range": "€€€",
                        "known_for": "The oldest café in Paris",
                        "atmosphere": "Historic and intellectual"
                    },
                    {
                        "name": "Café de Flore",
                        "cuisine": "French Café",
                        "price_range": "€€€",
                        "known_for": "Literary history and classic French café fare",
                        "atmosphere": "Elegant and bustling"
                    },
                    {
                        "name": "Le Comptoir du Panthéon",
                        "cuisine": "Bistro",
                        "price_range": "€€",
                        "known_for": "Traditional French dishes",
                        "atmosphere": "Casual and student-friendly"
                    }
                ],
                "activities": [
                    {
                        "name": "Visit the Sorbonne",
                        "type": "Educational tour",
                        "description": "Explore the historic university and its impact on Parisian academic life.",
                        "suitable_for": [
                            "Students",
                            "History buffs"
                        ]
                    },
                    {
                        "name": "Explore Rue Mouffetard",
                        "type": "Street market",
                        "description": "A lively market street offering fresh produce and local goods.",
                        "suitable_for": [
                            "Foodies",
                            "Families"
                        ]
                    }
                ]
            },
            "stay_here_if": [
                "You are a student or academic",
                "You enjoy historic and vibrant areas"
            ],
            "avoid_if": [
                "You prefer quieter, more modern districts",
                "You dislike crowded streets"
            ],
            "insider_tips": [
                "Discover hidden courtyards and ancient ruins around the Sorbonne.",
                "Try the ice cream at Berthillon on Île Saint-Louis nearby."
            ]
        },
        {
            "name": "Champs-Élysées",
            "alternate_names": [
                "Avenue des Champs-Élysées",
                "The Beautiful Avenue"
            ],
            "character": "A world-renowned avenue known for its luxury shops, theaters, and cafés.",
            "location": {
                "central": true,
                "description": "Located in the 8th arrondissement, stretching from the Place de la Concorde to the Arc de Triomphe.",
                "borders": [
                    "Place de la Concorde",
                    "Arc de Triomphe",
                    "Rond-Point des Champs-Élysées"
                ],
                "landmarks": [
                    "Arc de Triomphe",
                    "Palais de la Découverte"
                ]
            },
            "history": {
                "overview": "Originally fields and market gardens, transformed into a grand avenue in the 17th century.",
                "significance": "A symbol of Parisian luxury and grandeur, hosting military parades and celebrations.",
                "notable_events": [
                    "Bastille Day military parade",
                    "New Year's Eve celebrations"
                ]
            },
            "practical_info": {
                "transit": [
                    "Champs-Élysées - Clemenceau",
                    "Franklin D. Roosevelt",
                    "Charles de Gaulle - Étoile"
                ],
                "safety": "Safe but beware of pickpockets, especially during events.",
                "best_time_to_visit": "Evenings for the illuminated avenue and vibrant atmosphere.",
                "walkability": "Highly walkable with wide sidewalks."
            },
            "appeal": {
                "known_for": [
                    "Luxury shopping",
                    "Iconic landmarks",
                    "Theater and entertainment"
                ],
                "atmosphere": [
                    "Elegant",
                    "Bustling",
                    "Touristy"
                ],
                "best_for": [
                    "Shoppers",
                    "First-time visitors",
                    "Luxury travelers"
                ]
            },
            "categories": {
                "touristy": 5,
                "residential": 2,
                "green_spaces": 2,
                "shopping": 5,
                "dining": 4,
                "nightlife": 4,
                "cultural": 3,
                "historic": 4
            },
            "highlights": {
                "attractions": [
                    {
                        "name": "Arc de Triomphe",
                        "type": "Monument",
                        "description": "A monumental arch honoring those who fought and died for France.",
                        "appeal": "Climb to the top for stunning views of Paris."
                    },
                    {
                        "name": "Grand Palais",
                        "type": "Exhibition hall",
                        "description": "A historic site that hosts art exhibitions and cultural events.",
                        "appeal": "Marvel at its stunning glass-domed roof."
                    },
                    {
                        "name": "Lido de Paris",
                        "type": "Cabaret",
                        "description": "Enjoy a lavish cabaret show with dinner.",
                        "appeal": "Experience the glamour of Parisian nightlife."
                    }
                ],
                "dining": [
                    {
                        "name": "Ladurée",
                        "cuisine": "French Patisserie",
                        "price_range": "€€€",
                        "known_for": "Macarons and tea time",
                        "atmosphere": "Luxurious and elegant"
                    },
                    {
                        "name": "Le Fouquet's",
                        "cuisine": "French",
                        "price_range": "€€€€",
                        "known_for": "Classic French cuisine and celebrity clientele",
                        "atmosphere": "Sophisticated and historic"
                    },
                    {
                        "name": "Le Cinq",
                        "cuisine": "Fine Dining",
                        "price_range": "€€€€",
                        "known_for": "Michelin-starred cuisine and impeccable service",
                        "atmosphere": "Opulent and refined"
                    }
                ],
                "activities": [
                    {
                        "name": "Shopping Spree",
                        "type": "Retail therapy",
                        "description": "Explore luxury boutiques and flagship stores along the avenue.",
                        "suitable_for": [
                            "Shopaholics",
                            "Fashionistas"
                        ]
                    },
                    {
                        "name": "Attend a Show at Lido",
                        "type": "Entertainment",
                        "description": "Enjoy a glamorous cabaret show.",
                        "suitable_for": [
                            "Couples",
                            "Nightlife enthusiasts"
                        ]
                    }
                ]
            },
            "stay_here_if": [
                "You love luxury shopping and iconic landmarks",
                "You want to be in the heart of Parisian elegance"
            ],
            "avoid_if": [
                "You prefer quieter, less touristy areas",
                "You are on a tight budget"
            ],
            "insider_tips": [
                "Visit early in the morning to avoid crowds.",
                "Check out the Christmas lights during the holiday season."
            ]
        },
        {
            "name": "Le Marais",
            "alternate_names": [
                "The Marsh",
                "Jewish Quarter"
            ],
            "character": "A historic and vibrant area known for its narrow cobblestone streets and diverse cultural offerings.",
            "location": {
                "central": true,
                "description": "Located in the 3rd and 4th arrondissements on the Right Bank of the Seine.",
                "borders": [
                    "Bastille",
                    "Île de la Cité",
                    "République"
                ],
                "landmarks": [
                    "Place des Vosges",
                    "Musée Picasso"
                ]
            },
            "history": {
                "overview": "Originally a marshland, it became a royal district in the 17th century and later a Jewish quarter.",
                "significance": "Home to historic mansions and a vibrant Jewish community.",
                "notable_events": [
                    "The district's transformation in the 19th century",
                    "Significant Jewish migration"
                ]
            },
            "practical_info": {
                "transit": [
                    "Saint-Paul",
                    "Hôtel de Ville",
                    "Chemin Vert"
                ],
                "safety": "Generally safe with bustling streets, especially in tourist areas.",
                "best_time_to_visit": "Spring and early fall for pleasant weather.",
                "walkability": "Highly walkable with many pedestrian areas."
            },
            "appeal": {
                "known_for": [
                    "Art galleries",
                    "Boutique shopping",
                    "Historic architecture"
                ],
                "atmosphere": [
                    "Charming",
                    "Cultural",
                    "Trendy"
                ],
                "best_for": [
                    "Art lovers",
                    "History buffs",
                    "Fashion enthusiasts"
                ]
            },
            "categories": {
                "touristy": 4,
                "residential": 3,
                "green_spaces": 2,
                "shopping": 5,
                "dining": 5,
                "nightlife": 4,
                "cultural": 5,
                "historic": 5
            },
            "highlights": {
                "attractions": [
                    {
                        "name": "Place des Vosges",
                        "type": "Historic square",
                        "description": "The oldest planned square in Paris, surrounded by elegant 17th-century architecture.",
                        "appeal": "A beautiful and peaceful retreat in the heart of the city."
                    },
                    {
                        "name": "Musée Picasso",
                        "type": "Museum",
                        "description": "Houses over 5,000 works by Pablo Picasso.",
                        "appeal": "A must-visit for modern art enthusiasts."
                    },
                    {
                        "name": "Le Carreau du Temple",
                        "type": "Event venue",
                        "description": "A cultural venue hosting markets, exhibitions, and performances.",
                        "appeal": "Experience local arts and crafts in a historical setting."
                    }
                ],
                "dining": [
                    {
                        "name": "L'As du Fallafel",
                        "cuisine": "Middle Eastern",
                        "price_range": "€",
                        "known_for": "Famous falafel sandwiches",
                        "atmosphere": "Casual and lively"
                    },
                    {
                        "name": "Le Mary Celeste",
                        "cuisine": "Contemporary",
                        "price_range": "€€",
                        "known_for": "Oysters and creative cocktails",
                        "atmosphere": "Trendy with a nautical theme"
                    },
                    {
                        "name": "Chez Janou",
                        "cuisine": "Provençal",
                        "price_range": "€€",
                        "known_for": "Chocolate mousse and sunny terrace",
                        "atmosphere": "Cozy and Provencal"
                    }
                ],
                "activities": [
                    {
                        "name": "Art Gallery Tour",
                        "type": "Cultural activity",
                        "description": "Explore the numerous art galleries showcasing contemporary works.",
                        "suitable_for": [
                            "Art enthusiasts",
                            "Couples"
                        ]
                    },
                    {
                        "name": "Shopping at BHV Marais",
                        "type": "Shopping",
                        "description": "A large department store offering a variety of goods.",
                        "suitable_for": [
                            "Shoppers",
                            "Families"
                        ]
                    }
                ]
            },
            "stay_here_if": [
                "You love art and history",
                "You want to be in a trendy area with many dining options"
            ],
            "avoid_if": [
                "You prefer quieter, less crowded areas",
                "You need more green spaces"
            ],
            "insider_tips": [
                "Visit on a Sunday when most other stores in Paris are closed.",
                "Explore Rue des Rosiers for the best Jewish bakeries."
            ]
        },
        {
            "name": "Montparnasse",
            "alternate_names": [
                "The Left Bank"
            ],
            "character": "Once a bohemian hub, now a vibrant area with skyscrapers and a lively arts scene.",
            "location": {
                "central": false,
                "description": "Located in the 14th arrondissement on the Left Bank.",
                "borders": [
                    "Saint-Germain-des-Prés",
                    "Denfert-Rochereau",
                    "Parc Montsouris"
                ],
                "landmarks": [
                    "Montparnasse Tower",
                    "Cimetière Montparnasse"
                ]
            },
            "history": {
                "overview": "Known for its artistic and intellectual communities in the early 20th century.",
                "significance": "A center for artists and writers, including Hemingway and Fitzgerald.",
                "notable_events": [
                    "Artistic movements in the 1920s",
                    "Building of Montparnasse Tower"
                ]
            },
            "practical_info": {
                "transit": [
                    "Montparnasse-Bienvenüe",
                    "Raspail",
                    "Edgar Quinet"
                ],
                "safety": "Safe with a mix of residential and tourist areas.",
                "best_time_to_visit": "Evenings for vibrant nightlife and dining.",
                "walkability": "Very walkable with wide boulevards and small streets."
            },
            "appeal": {
                "known_for": [
                    "Artistic heritage",
                    "Cafés and brasseries",
                    "Modern architecture"
                ],
                "atmosphere": [
                    "Lively",
                    "Creative",
                    "Dynamic"
                ],
                "best_for": [
                    "Night owls",
                    "Art lovers",
                    "History buffs"
                ]
            },
            "categories": {
                "touristy": 3,
                "residential": 4,
                "green_spaces": 3,
                "shopping": 3,
                "dining": 4,
                "nightlife": 4,
                "cultural": 4,
                "historic": 3
            },
            "highlights": {
                "attractions": [
                    {
                        "name": "Montparnasse Tower",
                        "type": "Observation deck",
                        "description": "Offers panoramic views of Paris from its top floor.",
                        "appeal": "The best views of the Eiffel Tower in Paris."
                    },
                    {
                        "name": "Cimetière Montparnasse",
                        "type": "Cemetery",
                        "description": "Final resting place of many notable intellectuals and artists.",
                        "appeal": "A peaceful place with historical significance."
                    },
                    {
                        "name": "La Coupole",
                        "type": "Brasserie",
                        "description": "A historic brasserie famous for its Art Deco design.",
                        "appeal": "Experience Parisian dining in a classic setting."
                    }
                ],
                "dining": [
                    {
                        "name": "Le Dôme",
                        "cuisine": "Seafood",
                        "price_range": "€€€€",
                        "known_for": "Exquisite seafood dishes",
                        "atmosphere": "Elegant and historic"
                    },
                    {
                        "name": "La Rotonde",
                        "cuisine": "French",
                        "price_range": "€€€",
                        "known_for": "Iconic artist hangout",
                        "atmosphere": "Bohemian and lively"
                    },
                    {
                        "name": "La Crêperie de Josselin",
                        "cuisine": "Breton",
                        "price_range": "€€",
                        "known_for": "Authentic Breton crêpes",
                        "atmosphere": "Cozy and casual"
                    }
                ],
                "activities": [
                    {
                        "name": "Visit the Catacombs",
                        "type": "Historical tour",
                        "description": "Explore the underground ossuaries of Paris.",
                        "suitable_for": [
                            "History enthusiasts",
                            "Adventurous travelers"
                        ]
                    },
                    {
                        "name": "Explore Rue de la Gaîté",
                        "type": "Theater district",
                        "description": "Discover numerous theaters and live performances.",
                        "suitable_for": [
                            "Theater lovers",
                            "Couples"
                        ]
                    }
                ]
            },
            "stay_here_if": [
                "You enjoy vibrant nightlife and cultural history",
                "You want easy access to Left Bank attractions"
            ],
            "avoid_if": [
                "You prefer quieter neighborhoods",
                "You dislike modern architecture"
            ],
            "insider_tips": [
                "Visit the top of Montparnasse Tower at sunset.",
                "Try a classic French meal at one of the historic brasseries."
            ]
        },
        {
            "name": "La Défense",
            "alternate_names": [
                "Business District"
            ],
            "character": "A modern business district known for its skyscrapers and contemporary architecture.",
            "location": {
                "central": false,
                "description": "Located west of Paris in the Hauts-de-Seine department.",
                "borders": [
                    "Courbevoie",
                    "Puteaux",
                    "Nanterre"
                ],
                "landmarks": [
                    "Grande Arche",
                    "CNIT"
                ]
            },
            "history": {
                "overview": "Developed in the 1950s as a business district, it has grown into a major financial hub.",
                "significance": "Home to numerous multinational companies and a symbol of modernity.",
                "notable_events": [
                    "Opening of Grande Arche",
                    "Development of major corporate headquarters"
                ]
            },
            "practical_info": {
                "transit": [
                    "La Défense",
                    "Esplanade de La Défense"
                ],
                "safety": "Very safe, with a strong corporate presence.",
                "best_time_to_visit": "Weekdays for business activities, weekends for shopping and leisure.",
                "walkability": "Pedestrian-friendly with extensive walkways and plazas."
            },
            "appeal": {
                "known_for": [
                    "Modern architecture",
                    "Business activities",
                    "Shopping"
                ],
                "atmosphere": [
                    "Sleek",
                    "Corporate",
                    "Futuristic"
                ],
                "best_for": [
                    "Business travelers",
                    "Architectural enthusiasts",
                    "Shoppers"
                ]
            },
            "categories": {
                "touristy": 2,
                "residential": 2,
                "green_spaces": 3,
                "shopping": 4,
                "dining": 3,
                "nightlife": 2,
                "cultural": 2,
                "historic": 1
            },
            "highlights": {
                "attractions": [
                    {
                        "name": "Grande Arche",
                        "type": "Monument",
                        "description": "A modern architectural marvel and symbol of La Défense.",
                        "appeal": "Climb to the top for panoramic views of Paris."
                    },
                    {
                        "name": "Les Quatre Temps",
                        "type": "Shopping mall",
                        "description": "One of the largest shopping centers in Europe.",
                        "appeal": "Shop a wide range of brands under one roof."
                    },
                    {
                        "name": "CNIT",
                        "type": "Conference center",
                        "description": "A major venue for conferences and exhibitions.",
                        "appeal": "Experience business innovation and events."
                    }
                ],
                "dining": [
                    {
                        "name": "Vapiano",
                        "cuisine": "Italian",
                        "price_range": "€€",
                        "known_for": "Fresh pasta and pizzas",
                        "atmosphere": "Casual and contemporary"
                    },
                    {
                        "name": "L'Atelier Artisan Crêpier",
                        "cuisine": "Breton",
                        "price_range": "€€",
                        "known_for": "Creative crêpes and galettes",
                        "atmosphere": "Modern and inviting"
                    },
                    {
                        "name": "Taj Mahal",
                        "cuisine": "Indian",
                        "price_range": "€€",
                        "known_for": "Authentic Indian dishes",
                        "atmosphere": "Colorful and cozy"
                    }
                ],
                "activities": [
                    {
                        "name": "Architecture Tour",
                        "type": "Guided tour",
                        "description": "Explore the modern architectural wonders of La Défense.",
                        "suitable_for": [
                            "Architecture buffs",
                            "Students"
                        ]
                    },
                    {
                        "name": "Visit U Arena",
                        "type": "Sports and entertainment",
                        "description": "Attend concerts, sports events, and shows.",
                        "suitable_for": [
                            "Music lovers",
                            "Sports fans"
                        ]
                    }
                ]
            },
            "stay_here_if": [
                "You are on a business trip",
                "You appreciate modern architecture"
            ],
            "avoid_if": [
                "You seek a historic or traditional Parisian experience",
                "You want lively nightlife"
            ],
            "insider_tips": [
                "Visit during business hours to see the district in action.",
                "Explore the public art installations scattered around the area."
            ]
        },
        {
            "name": "Bastille",
            "alternate_names": [
                "Place de la Bastille"
            ],
            "character": "A lively area with a mix of historic significance and a vibrant nightlife.",
            "location": {
                "central": true,
                "description": "Situated in the 11th arrondissement, surrounding the Place de la Bastille.",
                "borders": [
                    "Le Marais",
                    "Oberkampf",
                    "Gare de Lyon"
                ],
                "landmarks": [
                    "Opéra Bastille",
                    "Place de la Bastille"
                ]
            },
            "history": {
                "overview": "The site of the former Bastille prison, a key location in the French Revolution.",
                "significance": "Symbol of the French Revolution and modern cultural resurgence.",
                "notable_events": [
                    "Storming of the Bastille",
                    "Bastille Day celebrations"
                ]
            },
            "practical_info": {
                "transit": [
                    "Bastille",
                    "Ledru-Rollin",
                    "Bréguet-Sabin"
                ],
                "safety": "Generally safe, but exercise caution at night.",
                "best_time_to_visit": "Evenings for dining and nightlife.",
                "walkability": "Highly walkable with lively streets."
            },
            "appeal": {
                "known_for": [
                    "Nightlife",
                    "History",
                    "Cafés and bars"
                ],
                "atmosphere": [
                    "Energetic",
                    "Historic",
                    "Trendy"
                ],
                "best_for": [
                    "Night owls",
                    "History enthusiasts",
                    "Young travelers"
                ]
            },
            "categories": {
                "touristy": 4,
                "residential": 3,
                "green_spaces": 2,
                "shopping": 3,
                "dining": 4,
                "nightlife": 5,
                "cultural": 4,
                "historic": 4
            },
            "highlights": {
                "attractions": [
                    {
                        "name": "Opéra Bastille",
                        "type": "Opera house",
                        "description": "A modern opera house with a diverse program of performances.",
                        "appeal": "Enjoy world-class opera and ballet."
                    },
                    {
                        "name": "Place de la Bastille",
                        "type": "Historical site",
                        "description": "A bustling square with historic and cultural significance.",
                        "appeal": "Visit the July Column and learn about the Revolution."
                    },
                    {
                        "name": "Marché Bastille",
                        "type": "Market",
                        "description": "A popular open-air market offering fresh produce and local goods.",
                        "appeal": "Experience local flavors and Parisian market culture."
                    }
                ],
                "dining": [
                    {
                        "name": "Le Café des Anges",
                        "cuisine": "French",
                        "price_range": "€€",
                        "known_for": "Casual dining with a Parisian flair",
                        "atmosphere": "Lively and friendly"
                    },
                    {
                        "name": "Blue Elephant",
                        "cuisine": "Thai",
                        "price_range": "€€€",
                        "known_for": "Authentic Thai cuisine",
                        "atmosphere": "Exotic and elegant"
                    },
                    {
                        "name": "Barrio Latino",
                        "cuisine": "Latin American",
                        "price_range": "€€€",
                        "known_for": "Latin music and dance",
                        "atmosphere": "Vibrant and festive"
                    }
                ],
                "activities": [
                    {
                        "name": "Bar Hopping",
                        "type": "Nightlife",
                        "description": "Experience the diverse bar scene in Bastille.",
                        "suitable_for": [
                            "Young adults",
                            "Couples"
                        ]
                    },
                    {
                        "name": "Attend a Performance at Opéra Bastille",
                        "type": "Cultural event",
                        "description": "Enjoy a world-class opera or ballet performance.",
                        "suitable_for": [
                            "Culture enthusiasts",
                            "Music lovers"
                        ]
                    }
                ]
            },
            "stay_here_if": [
                "You love vibrant nightlife and historic surroundings",
                "You want to explore a lively cultural scene"
            ],
            "avoid_if": [
                "You prefer quiet neighborhoods",
                "You are traveling with small children"
            ],
            "insider_tips": [
                "Check out the local bars for live music.",
                "Visit the market early for the best selection."
            ]
        },
        {
            "name": "Belleville",
            "alternate_names": [
                "Multicultural District"
            ],
            "character": "A diverse and multicultural neighborhood known for its street art and vibrant community.",
            "location": {
                "central": false,
                "description": "Located in the 19th and 20th arrondissements, northeast of the city center.",
                "borders": [
                    "Ménilmontant",
                    "Père Lachaise",
                    "Canal Saint-Martin"
                ],
                "landmarks": [
                    "Parc de Belleville",
                    "Rue Dénoyez"
                ]
            },
            "history": {
                "overview": "Historically a working-class district, it has become a center for multiculturalism and creativity.",
                "significance": "Known for its immigrant communities and artistic flair.",
                "notable_events": [
                    "Rise of street art culture",
                    "Annual Belleville Artists' Open Studios"
                ]
            },
            "practical_info": {
                "transit": [
                    "Belleville",
                    "Couronnes",
                    "Pyrénées"
                ],
                "safety": "Generally safe, but stay vigilant in less busy areas at night.",
                "best_time_to_visit": "Spring and summer for outdoor activities and festivals.",
                "walkability": "Very walkable with hilly terrain offering great views."
            },
            "appeal": {
                "known_for": [
                    "Street art",
                    "Multicultural cuisine",
                    "Vibrant arts scene"
                ],
                "atmosphere": [
                    "Eclectic",
                    "Bohemian",
                    "Dynamic"
                ],
                "best_for": [
                    "Artists",
                    "Foodies",
                    "Young travelers"
                ]
            },
            "categories": {
                "touristy": 3,
                "residential": 4,
                "green_spaces": 3,
                "shopping": 3,
                "dining": 4,
                "nightlife": 3,
                "cultural": 4,
                "historic": 2
            },
            "highlights": {
                "attractions": [
                    {
                        "name": "Parc de Belleville",
                        "type": "Public park",
                        "description": "Offers panoramic views of Paris and beautiful gardens.",
                        "appeal": "A peaceful retreat with stunning vistas."
                    },
                    {
                        "name": "Rue Dénoyez",
                        "type": "Street art",
                        "description": "A vibrant street covered in colorful murals and graffiti.",
                        "appeal": "Discover the heart of Parisian street art culture."
                    },
                    {
                        "name": "Père Lachaise Cemetery",
                        "type": "Cemetery",
                        "description": "Final resting place of many famous figures.",
                        "appeal": "Visit the graves of Jim Morrison and Oscar Wilde."
                    }
                ],
                "dining": [
                    {
                        "name": "Le Baratin",
                        "cuisine": "French Bistro",
                        "price_range": "€€€",
                        "known_for": "Inventive French cuisine",
                        "atmosphere": "Cozy and intimate"
                    },
                    {
                        "name": "La Cave de Belleville",
                        "cuisine": "Wine Bar",
                        "price_range": "€€",
                        "known_for": "Natural wines and cheese platters",
                        "atmosphere": "Casual and friendly"
                    },
                    {
                        "name": "Dong Huong",
                        "cuisine": "Vietnamese",
                        "price_range": "€€",
                        "known_for": "Pho and banh mi",
                        "atmosphere": "Authentic and bustling"
                    }
                ],
                "activities": [
                    {
                        "name": "Street Art Tour",
                        "type": "Guided tour",
                        "description": "Explore the vibrant street art scene with a local guide.",
                        "suitable_for": [
                            "Art enthusiasts",
                            "Young travelers"
                        ]
                    },
                    {
                        "name": "Explore Belleville Market",
                        "type": "Market",
                        "description": "A bustling market offering fresh produce and multicultural foods.",
                        "suitable_for": [
                            "Foodies",
                            "Families"
                        ]
                    }
                ]
            },
            "stay_here_if": [
                "You enjoy multicultural environments and vibrant arts scenes",
                "You want to explore a less touristy area"
            ],
            "avoid_if": [
                "You seek a more traditional Parisian experience",
                "You prefer upscale shopping"
            ],
            "insider_tips": [
                "Check out the local art studios during open house events.",
                "Try the Vietnamese food for an authentic experience."
            ]
        },
        {
            "name": "Canal Saint-Martin",
            "alternate_names": [
                "The Canal",
                "Hipster Haven"
            ],
            "character": "A trendy, picturesque area known for its bohemian vibe and scenic canalside walks.",
            "location": {
                "central": true,
                "description": "Located in the 10th arrondissement, stretching from the Place de la République to the Bassin de la Villette.",
                "borders": [
                    "République",
                    "Belleville",
                    "Gare du Nord"
                ],
                "landmarks": [
                    "Canal Saint-Martin",
                    "Jardin Villemin"
                ]
            },
            "history": {
                "overview": "Originally built in the early 19th century to supply Paris with fresh water.",
                "significance": "Revitalized as a trendy area with a laid-back atmosphere.",
                "notable_events": [
                    "Recent gentrification",
                    "Film location for 'Amélie'"
                ]
            },
            "practical_info": {
                "transit": [
                    "Jacques Bonsergent",
                    "Gare de l'Est",
                    "République"
                ],
                "safety": "Safe during the day but exercise caution at night.",
                "best_time_to_visit": "Summer for outdoor dining and canal activities.",
                "walkability": "Very walkable with charming bridges and pathways."
            },
            "appeal": {
                "known_for": [
                    "Scenic canals",
                    "Bohemian cafés",
                    "Artisanal shops"
                ],
                "atmosphere": [
                    "Trendy",
                    "Relaxed",
                    "Artistic"
                ],
                "best_for": [
                    "Young professionals",
                    "Couples",
                    "Photographers"
                ]
            },
            "categories": {
                "touristy": 3,
                "residential": 4,
                "green_spaces": 3,
                "shopping": 3,
                "dining": 4,
                "nightlife": 3,
                "cultural": 3,
                "historic": 2
            },
            "highlights": {
                "attractions": [
                    {
                        "name": "Canal Saint-Martin",
                        "type": "Waterway",
                        "description": "A picturesque canal lined with trees and iron footbridges.",
                        "appeal": "Perfect for a leisurely stroll or picnic by the water."
                    },
                    {
                        "name": "Jardin Villemin",
                        "type": "Public garden",
                        "description": "A peaceful park with beautiful gardens and a playground.",
                        "appeal": "Ideal for relaxation and family outings."
                    },
                    {
                        "name": "Antoine et Lili",
                        "type": "Boutique",
                        "description": "Colorful shops offering unique fashion and home goods.",
                        "appeal": "Discover eclectic and vibrant shopping options."
                    }
                ],
                "dining": [
                    {
                        "name": "Le Comptoir Général",
                        "cuisine": "Global",
                        "price_range": "€€",
                        "known_for": "Eclectic decor and diverse menu",
                        "atmosphere": "Quirky and lively"
                    },
                    {
                        "name": "Hotel du Nord",
                        "cuisine": "French",
                        "price_range": "€€€",
                        "known_for": "Classic French dishes",
                        "atmosphere": "Historic and cozy"
                    },
                    {
                        "name": "Chez Prune",
                        "cuisine": "French Bistro",
                        "price_range": "€€",
                        "known_for": "Charming canal-side setting",
                        "atmosphere": "Casual and inviting"
                    }
                ],
                "activities": [
                    {
                        "name": "Canal Boat Tour",
                        "type": "Boat tour",
                        "description": "Explore the canal by boat for a unique perspective.",
                        "suitable_for": [
                            "Families",
                            "Couples"
                        ]
                    },
                    {
                        "name": "Picnic by the Canal",
                        "type": "Outdoor activity",
                        "description": "Enjoy a relaxing picnic along the canal's banks.",
                        "suitable_for": [
                            "Families",
                            "Friends"
                        ]
                    }
                ]
            },
            "stay_here_if": [
                "You enjoy relaxed, trendy environments with a bohemian flair",
                "You want to experience local life by the water"
            ],
            "avoid_if": [
                "You prefer more historic or upscale neighborhoods",
                "You seek vibrant nightlife"
            ],
            "insider_tips": [
                "Visit early morning for peaceful walks.",
                "Check out the local markets for fresh produce and snacks."
            ]
        },
        {
            "name": "Île de la Cité",
            "alternate_names": [
                "The Island",
                "Heart of Paris"
            ],
            "character": "A historic island in the Seine, home to some of Paris's most iconic landmarks.",
            "location": {
                "central": true,
                "description": "Located in the Seine River, in the center of Paris.",
                "borders": [
                    "Île Saint-Louis",
                    "Le Marais",
                    "Saint-Germain-des-Prés"
                ],
                "landmarks": [
                    "Notre-Dame Cathedral",
                    "Sainte-Chapelle"
                ]
            },
            "history": {
                "overview": "The historical center of Paris, inhabited since ancient times.",
                "significance": "Site of the original city of Paris, with rich historical and architectural heritage.",
                "notable_events": [
                    "Construction of Notre-Dame",
                    "Medieval religious and royal ceremonies"
                ]
            },
            "practical_info": {
                "transit": [
                    "Cité",
                    "Saint-Michel",
                    "Pont Neuf"
                ],
                "safety": "Very safe, with a constant presence of tourists and police.",
                "best_time_to_visit": "Spring and autumn for mild weather and fewer crowds.",
                "walkability": "Highly walkable with most attractions within close proximity."
            },
            "appeal": {
                "known_for": [
                    "Gothic architecture",
                    "Historic sites",
                    "River views"
                ],
                "atmosphere": [
                    "Historic",
                    "Picturesque",
                    "Touristy"
                ],
                "best_for": [
                    "History lovers",
                    "First-time visitors",
                    "Photographers"
                ]
            },
            "categories": {
                "touristy": 5,
                "residential": 1,
                "green_spaces": 2,
                "shopping": 2,
                "dining": 3,
                "nightlife": 2,
                "cultural": 5,
                "historic": 5
            },
            "highlights": {
                "attractions": [
                    {
                        "name": "Notre-Dame Cathedral",
                        "type": "Cathedral",
                        "description": "A masterpiece of French Gothic architecture.",
                        "appeal": "Climb the towers for a stunning view of Paris."
                    },
                    {
                        "name": "Sainte-Chapelle",
                        "type": "Chapel",
                        "description": "Renowned for its stunning stained-glass windows.",
                        "appeal": "Experience the breathtaking beauty of medieval glass art."
                    },
                    {
                        "name": "Conciergerie",
                        "type": "Historic site",
                        "description": "A former royal palace and prison during the French Revolution.",
                        "appeal": "Explore the history of one of Paris's oldest buildings."
                    }
                ],
                "dining": [
                    {
                        "name": "Au Vieux Paris d'Arcole",
                        "cuisine": "French",
                        "price_range": "€€€",
                        "known_for": "Historic charm and classic dishes",
                        "atmosphere": "Cozy and romantic"
                    },
                    {
                        "name": "Le Saint Régis",
                        "cuisine": "French Café",
                        "price_range": "€€",
                        "known_for": "Traditional café culture",
                        "atmosphere": "Charming and bustling"
                    },
                    {
                        "name": "Brasserie Les Deux Palais",
                        "cuisine": "French",
                        "price_range": "€€",
                        "known_for": "Classic brasserie menu",
                        "atmosphere": "Elegant and spacious"
                    }
                ],
                "activities": [
                    {
                        "name": "Explore Notre-Dame",
                        "type": "Historical tour",
                        "description": "Visit the iconic cathedral and its surroundings.",
                        "suitable_for": [
                            "History buffs",
                            "Families"
                        ]
                    },
                    {
                        "name": "Visit Sainte-Chapelle",
                        "type": "Cultural activity",
                        "description": "Marvel at the stained glass and Gothic architecture.",
                        "suitable_for": [
                            "Art lovers",
                            "Couples"
                        ]
                    }
                ]
            },
            "stay_here_if": [
                "You want to be at the heart of Paris's historic and cultural sites",
                "You love exploring iconic architecture"
            ],
            "avoid_if": [
                "You prefer quieter, less touristy areas",
                "You seek a modern atmosphere"
            ],
            "insider_tips": [
                "Visit Sainte-Chapelle on a sunny day to see the stained glass at its best.",
                "Explore the nearby flower market for a unique experience."
            ]
        }
    ]
}