{
    "November": {
        "reasons_to_visit": [
            {
                "reason": "Low Season Tranquility",
                "details": "November is one of Turin's quietest months. Experience major sites like the Royal Palace, Egyptian Museum, and Mole Antonelliana with minimal crowds and a relaxed atmosphere."
            },
            {
                "reason": "Cool Alpine Autumn/Winter",
                "details": "Turin's November weather showcases the transition to winter, with crisp air, occasional fog, and the potential for first snowfall on surrounding mountains."
            },
            {
                "reason": "Authentic Local Experience",
                "details": "With few tourists, November offers a chance to see Turin as the locals live it, exploring markets, historic cafés, and neighborhoods authentically."
            },
            {
                "reason": "Budget-Friendly Travel",
                "details": "Benefit from low season prices on flights and accommodation, making a trip to Turin much more affordable than during peak periods."
            },
            {
                "reason": "Autumnal Piedmontese Cuisine",
                "details": "Savor hearty fall dishes like bagna cauda, tajarin pasta with truffles, seasonal produce like chestnuts and mushrooms, new Piedmont wines, and chocolate specialties."
            },
            {
                "reason": "Focus on Indoor Culture",
                "details": "Ideal month for leisurely exploration of Turin's rich collection of museums, royal palaces, churches, and performances at Teatro Regio."
            }
        ],
        "reasons_to_reconsider": [
            {
                "reason": "Cold and Wet Weather",
                "details": "November is one of Turin's coldest and greyest months. Be prepared for chilly days and potential fog that might disrupt views of the Alps."
            },
            {
                "reason": "Shorter Daylight Hours",
                "details": "Days are significantly shorter, with sunset around 4:45-5:00 PM, limiting time for outdoor activities and sightseeing in natural light."
            },
            {
                "reason": "Cold Temperatures",
                "details": "Temperatures can be quite cold, especially evenings and mornings. Outdoor activities require proper winter clothing."
            },
            {
                "reason": "Some Potential Closures",
                "details": "Some tourist-oriented businesses or attractions might have reduced hours or temporary closures during the deep low season."
            }
        ],
        "first_half": {
            "date_range": "November 1–15",
            "weather": {
                "average_temperature": {
                    "high": "10°C",
                    "low": "3°C"
                },
                "precipitation": "Moderate chance of rain or occasional light snow. Fog is common, especially in the mornings. Grey skies predominate.",
                "general_tips": "Pack winter layers, including a warm coat, scarf, hat, and gloves. An umbrella and waterproof footwear are essential."
            },
            "tourism_level": {
                "crowds": "Very low. Attractions are quiet, offering an unhurried experience. Noticeable local activity around All Saints'/Souls' Day.",
                "pricing": "Low season prices offer excellent value for accommodation and flights.",
                "overall_atmosphere": "Quiet and authentic. Local life dominates, especially around the holidays at the beginning of the month."
            },
            "events_holidays": [
                {
                    "name": "All Saints' Day (Ognissanti)",
                    "date": "November 1",
                    "description": "National public holiday. Traditionally, families visit cemeteries to honor the deceased.",
                    "notes": "Expect closures of shops, banks, and some museums. Public transport on holiday schedule."
                },
                {
                    "name": "All Souls' Day (Giorno dei Morti)",
                    "date": "November 2",
                    "description": "Culturally significant day for remembering the dead. Look for special pastries in Turin's bakeries and cafés during these days.",
                    "notes": "Not a public holiday, but cemeteries are very busy. Visit the Monumental Cemetery of Turin for a cultural experience."
                },
                 {
                    "name": "Cioccolatò",
                    "date": "Usually mid-November",
                    "description": "Turin's famous chocolate festival might take place, celebrating the city's historic connection to chocolate making.",
                    "notes": "Check exact dates. Features tastings, demonstrations, and special chocolate creations."
                }
            ],
            "unique_experiences": [
                {
                    "activity": "Visit Palazzo Reale & Royal Museums",
                    "where": "Piazzetta Reale",
                    "description": "Explore the Royal Palace and its museums with virtually no crowds, allowing for detailed appreciation of the royal apartments and collections.",
                    "practical_tips": "Check opening hours, may be affected by Nov 1 holiday. Closed Mondays.",
                    "best_time": "Anytime during opening hours",
                    "estimated_cost": "Moderate to High",
                    "weather_dependent": false
                },
                {
                    "activity": "Warm Up with Hot Chocolate and Bicerin",
                    "where": "Historic cafés city-wide",
                    "description": "Try Turin's famous hot chocolate and bicerin (layered drink of chocolate, coffee and cream) in one of the historic cafés.",
                    "practical_tips": "Visit Caffè Al Bicerin (the original), Baratti & Milano, or Caffè Torino for authentic experiences.",
                    "best_time": "Afternoon",
                    "estimated_cost": "Low to Moderate",
                    "weather_dependent": false
                },
                {
                    "activity": "Visit Turin Cathedral & Holy Shroud Chapel",
                    "where": "Via XX Settembre",
                    "description": "Visit the Renaissance cathedral and the chapel that houses the Shroud of Turin (though the Shroud itself is rarely displayed).",
                    "practical_tips": "The cathedral offers a peaceful respite from the cold. The Shroud is not visible except during special exhibitions.",
                    "best_time": "Daytime",
                    "estimated_cost": "Free",
                    "weather_dependent": false
                },
                {
                    "activity": "Explore Porta Palazzo Market",
                    "where": "Piazza della Repubblica",
                    "description": "Experience Europe's largest open-air market, seeing seasonal produce like chestnuts, mushrooms, and truffles without tourist crowds.",
                    "practical_tips": "Best in the morning. Closes early afternoon. Partly indoors, good for colder days.",
                    "best_time": "Morning",
                    "estimated_cost": "Low",
                    "weather_dependent": false
                },
                {
                    "activity": "Visit the Egyptian Museum (Museo Egizio)",
                    "where": "Via Accademia delle Scienze",
                    "description": "Ideal indoor activity for a cold day, exploring the world's oldest Egyptian museum with the second largest collection after Cairo.",
                    "practical_tips": "Check opening hours. Allow 2-3 hours. Closed Mondays.",
                    "best_time": "Anytime (good for cold/wet days)",
                    "estimated_cost": "Moderate",
                    "weather_dependent": false
                },
                {
                    "activity": "Relax in a Historic Café",
                    "where": "Various city center locations",
                    "description": "Enjoy coffee, hot chocolate, and pastries in Turin's historic cafés, soaking up the elegant atmosphere and local traditions.",
                    "practical_tips": "Try Caffè San Carlo, Caffè Fiorio, or Caffè Mulassano for authentic 19th-century ambiance.",
                    "best_time": "Mid-morning or afternoon",
                    "estimated_cost": "Low to Moderate",
                    "weather_dependent": false
                }
            ]
        },
        "second_half": {
            "date_range": "November 16–30",
            "weather": {
                "average_temperature": {
                    "high": "8°C",
                    "low": "1°C"
                },
                "precipitation": "Increased chance of rain or first snow, especially towards the end of the month. Fog can be persistent, sometimes all day.",
                "general_tips": "Full winter clothing required. Layer for indoor heating and cold outdoors. Consider thermal underwear."
            },
            "tourism_level": {
                "crowds": "Extremely low. This is Turin's quietest period for tourism.",
                "pricing": "Lowest prices of the year for flights and accommodation. Excellent deals available.",
                "overall_atmosphere": "Very quiet and local. Winter atmosphere with early Christmas decorations and markets potentially starting to appear by the end of the month."
            },
            "events_holidays": [
                {
                    "name": "Opera and Classical Music Season",
                    "date": "Throughout November",
                    "description": "Check schedules for Teatro Regio, Auditorium RAI, and other venues for opera, concerts, and performances.",
                    "notes": "Good month for indoor cultural events. Book tickets in advance."
                }
            ],
            "unique_experiences": [
                {
                    "activity": "Mole Antonelliana & Cinema Museum",
                    "where": "Via Montebello",
                    "description": "Visit Turin's iconic landmark and the fascinating National Museum of Cinema housed inside. The views from the panoramic elevator are especially atmospheric in winter.",
                    "practical_tips": "Book tickets online. Take the glass elevator to the viewing platform for city views (weather permitting).",
                    "best_time": "Morning or afternoon",
                    "estimated_cost": "Moderate",
                    "weather_dependent": false
                },
                {
                    "activity": "Teatro Regio Performance",
                    "where": "Piazza Castello",
                    "description": "Attend an opera, ballet, or concert at Turin's prestigious opera house as the main season gets underway.",
                    "practical_tips": "Book performance tickets in advance. Dress formally for evening performances.",
                    "best_time": "Evening",
                    "estimated_cost": "Moderate to High",
                    "weather_dependent": false
                },
                {
                    "activity": "Visit GAM (Gallery of Modern Art)",
                    "where": "Via Magenta",
                    "description": "Explore modern and contemporary art in Turin's main modern art gallery, a great indoor option.",
                    "practical_tips": "Check opening hours. Closed Mondays.",
                    "best_time": "Anytime during opening hours",
                    "estimated_cost": "Moderate",
                    "weather_dependent": false
                },
                {
                    "activity": "Explore Turin's Underground",
                    "where": "Various locations",
                    "description": "Take a guided tour of Turin's underground spaces, including Roman ruins, medieval foundations, and air raid shelters.",
                    "practical_tips": "Book through Torino Sotterranea or similar tour operators. Tours are limited, so reserve early.",
                    "best_time": "According to tour schedule",
                    "estimated_cost": "Moderate",
                    "weather_dependent": false
                },
                {
                    "activity": "Piedmontese Cooking Class",
                    "where": "Various cooking schools",
                    "description": "Learn to cook hearty Piedmontese autumn/winter dishes like bagna cauda, brasato al Barolo, or tajarin with white truffles.",
                    "practical_tips": "Perfect activity for a cold day. Book in advance.",
                    "best_time": "Usually morning/lunchtime",
                    "estimated_cost": "High",
                    "weather_dependent": false
                },
                {
                    "activity": "Wine Tasting Experience",
                    "where": "Wine bars and enotecas",
                    "description": "Sample Piedmont's renowned wines like Barolo, Barbaresco, and Barbera from nearby wine regions, perfect for cold evenings.",
                    "practical_tips": "Try enotecas like Enoteca Botz or wine bars in the city center. Consider day trips to nearby wine regions if weather permits.",
                    "best_time": "Late afternoon or evening",
                    "estimated_cost": "Moderate to High",
                    "weather_dependent": false
                }
            ]
        }
    }
}